{
  "site-title": "Not-Equal.tech",
  "footer-images": {
    "images": [
      {
        "image": "/uploads/ukri.png",
        "caption": "UKRI - EPSRC"
      },
      {
        "image": "/uploads/ol.png",
        "caption": "Openly"
      },
      {
        "image": "/uploads/us.png",
        "caption": "University of Sussex"
      },
      {
        "image": "/uploads/rh.png",
        "caption": "Royal Holloway University"
      },
      {
        "image": "/uploads/sw.png",
        "caption": "Swansea University"
      }
    ]
  }
}